README.rst
setup.py
jocker/__init__.py
jocker/cli.py
jocker/jocker.py
jocker/jocker_config.py
jocker.egg-info/PKG-INFO
jocker.egg-info/SOURCES.txt
jocker.egg-info/dependency_links.txt
jocker.egg-info/entry_points.txt
jocker.egg-info/requires.txt
jocker.egg-info/top_level.txt