Metadata-Version: 1.1
Name: jocker
Version: 0.0.2
Summary: Jinja2 Based Dockerfile and Image Generator
Home-page: https://github.com/nir0s/jocker
Author: nir0s
Author-email: nir36g@gmail.com
License: LICENSE
Download-URL: https://github.com/nir0s/jocker/tarball/0.1
Platform: All
Classifier: Programming Language :: Python
Classifier: Development Status :: 3 - Alpha
Classifier: Natural Language :: English
Classifier: Environment :: Console
Classifier: Intended Audience :: Developers
Classifier: Intended Audience :: Information Technology
Classifier: Intended Audience :: System Administrators
Classifier: License :: OSI Approved :: Apache Software License
Classifier: Operating System :: POSIX :: Linux
Classifier: Operating System :: Microsoft
Classifier: Topic :: Software Development :: Libraries :: Python Modules
